django_formtools_addons-0.1.36.dist-info/DESCRIPTION.rst
django_formtools_addons-0.1.36.dist-info/METADATA
django_formtools_addons-0.1.36.dist-info/metadata.json
django_formtools_addons-0.1.36.dist-info/RECORD
django_formtools_addons-0.1.36.dist-info/top_level.txt
django_formtools_addons-0.1.36.dist-info/WHEEL
formtools_addons/__init__.py
formtools_addons/enums.py
formtools_addons/middleware.py
formtools_addons/models.py
formtools_addons/static/formtools_addons/css/formtools_addons.css
formtools_addons/static/formtools_addons/js/wizardapi.js
formtools_addons/static/formtools_addons/templates/directives/wizardapi/wizard.html
formtools_addons/templates/formtools_addons/wizard/wizard_form.html
formtools_addons/wizard/__init__.py
formtools_addons/wizard/views/__init__.py
formtools_addons/wizard/views/multipleformwizard.py
formtools_addons/wizard/views/wizardapi.py
