Metadata-Version: 1.1
Name: django-formtools-addons
Version: 0.1.36
Summary: 'Addons for Django Formtools'
Home-page: https://github.com/vikingco/django-formtools-addons
Author: VikingCo
Author-email: technology@vikingco.com
License: BSD
Keywords: django-formtools-addons
Platform: UNKNOWN
Classifier: Development Status :: 3 - Alpha
Classifier: Framework :: Django
Classifier: Framework :: Django :: 1.8
Classifier: Framework :: Django :: 1.9
Classifier: Intended Audience :: Developers
Classifier: License :: OSI Approved :: BSD License
Classifier: Natural Language :: English
Classifier: Programming Language :: Python :: 2
Classifier: Programming Language :: Python :: 2.7
Classifier: Programming Language :: Python :: 3
Classifier: Programming Language :: Python :: 3.3
Classifier: Programming Language :: Python :: 3.4
Classifier: Programming Language :: Python :: 3.5
